pls/__init__.py
pls/cmd.py
pls/static/version
pls/static/dot_pls/cc_instrument.sh
pls/static/dot_pls/export_gdb_or_lldb.sh
pls/static/dot_pls/git_clone.sh
pls/static/dot_pls/pls_h_dir/pls.h
pls/static/dot_vscode/launch.json
pls/static/dot_vscode/settings.json
pls/static/dot_vscode/tasks.json
plsbuild-0.3.dist-info/licenses/LICENSE
plsbuild-0.3.dist-info/METADATA
plsbuild-0.3.dist-info/WHEEL
plsbuild-0.3.dist-info/entry_points.txt
plsbuild-0.3.dist-info/top_level.txt
plsbuild-0.3.dist-info/RECORD
