Metadata-Version: 2.4
Name: plsbuild
Version: 0.3
Summary: C/C++ Build Tool
Author: Dima Korolev
Author-email: dima@current.ai
License-File: LICENSE
Dynamic: author
Dynamic: author-email
Dynamic: license-file
Dynamic: summary
